{
  "code": "BIPN 142",
  "name": "Systems Neurobiology",
  "department": "BIPN",
  "id": "142",
  "notes": [],
  "events_single": {
    "8cf56a9cf51328cb621be1cfc86931c582ba7acaccd035b02911c2a55f8911ca": {
      "sectxt": false,
      "sectionID": "",
      "type": "FI",
      "section": "03/20/2018",
      "days": "Tu",
      "time": "8:00a-10:59a",
      "building": "TBA",
      "room": "TBA",
      "instructors": [],
      "date": "2018-03-20T07:00:00.000Z",
      "start_time": "08:00",
      "end_time": "10:59"
    }
  },
  "events_unknown": [],
  "events_repeating": {
    "M": {
      "3d4f1dd59eb210feee7401d8522ea7d0c3c0cdea154ed33bdf724ff7f3e2405d": {
        "sectxt": true,
        "sectionID": "926231",
        "type": "DI",
        "section": "A01",
        "days": "M",
        "time": "5:00p-5:50p",
        "building": "YORK",
        "room": "3000A",
        "instructors": [
          "Wang, Jing"
        ],
        "start_time": "17:00",
        "end_time": "17:50"
      },
      "0ed645b278b7f3bf3bde57c70dca2cea91501bd0b4e9159138734be413c315dc": {
        "sectxt": true,
        "sectionID": "926232",
        "type": "DI",
        "section": "A02",
        "days": "M",
        "time": "6:00p-6:50p",
        "building": "YORK",
        "room": "3000A",
        "instructors": [
          "Wang, Jing"
        ],
        "start_time": "18:00",
        "end_time": "18:50"
      }
    },
    "Tu": {
      "0f7d781b39fc3dac4870e89604bd23b7a2b73737ef6916b2a214214635fb5215": {
        "sectxt": true,
        "sectionID": "",
        "type": "LE",
        "section": "A00",
        "days": "TuTh",
        "time": "9:30a-10:50a",
        "building": "SOLIS",
        "room": "104",
        "instructors": [
          "Wang, Jing"
        ],
        "start_time": "09:30",
        "end_time": "10:50"
      },
      "c96e696c60c64f88cf39b5058ed3fd228a31ab31dee6e2a17e30204b7cb9fcca": {
        "sectxt": true,
        "sectionID": "926234",
        "type": "DI",
        "section": "A04",
        "days": "Tu",
        "time": "8:00a-8:50a",
        "building": "HSS",
        "room": "1305",
        "instructors": [
          "Wang, Jing"
        ],
        "start_time": "08:00",
        "end_time": "08:50"
      }
    },
    "W": {
      "1365b9660b9249ec218729f089ad2bfd798ef7cb23c52a4d2aeb7bdfd318f26b": {
        "sectxt": true,
        "sectionID": "926235",
        "type": "DI",
        "section": "A05",
        "days": "W",
        "time": "8:00a-8:50a",
        "building": "HSS",
        "room": "1305",
        "instructors": [
          "Wang, Jing"
        ],
        "start_time": "08:00",
        "end_time": "08:50"
      }
    },
    "Th": {
      "8ff098b8a2d6a5ed531d26affe93f7932dee87af0cd128e2a5b96b5778f96a32": {
        "sectxt": true,
        "sectionID": "",
        "type": "LE",
        "section": "A00",
        "days": "TuTh",
        "time": "9:30a-10:50a",
        "building": "SOLIS",
        "room": "104",
        "instructors": [
          "Wang, Jing"
        ],
        "start_time": "09:30",
        "end_time": "10:50"
      }
    }
  },
  "sections": [
    "A"
  ]
}
