{
  "code": "EDS 136",
  "name": "Intro/Acad Tut/Second Schl Std",
  "department": "EDS",
  "id": "136",
  "notes": [],
  "events_single": {},
  "events_unknown": [],
  "events_repeating": {
    "M": {
      "68965a72837c749dee50d582e3cbb3d5c23c9a5c7e2d35e9bd6b69bc902faa6d": {
        "sectxt": true,
        "sectionID": "",
        "type": "LE",
        "section": "A00",
        "days": "M",
        "time": "3:00p-4:50p",
        "building": "PCYNH",
        "room": "340",
        "instructors": [
          "Chung, Luz Marina"
        ],
        "start_time": "15:00",
        "end_time": "16:50"
      },
      "3dc97f2dd957095d828e915f718a53098e77b77db265e25350921aa5e5f379d5": {
        "sectxt": true,
        "sectionID": "922492",
        "type": "DI",
        "section": "A01",
        "days": "M",
        "time": "5:00p-5:50p",
        "building": "PCYNH",
        "room": "304",
        "instructors": [
          "Chung, Luz Marina"
        ],
        "start_time": "17:00",
        "end_time": "17:50"
      },
      "13f1f94d8cc0be6008948ef3a21446e8f6e0894cff7e0e4f249d19b5e19768d3": {
        "sectxt": true,
        "sectionID": "922493",
        "type": "DI",
        "section": "A02",
        "days": "M",
        "time": "5:00p-5:50p",
        "building": "PCYNH",
        "room": "302",
        "instructors": [
          "Chung, Luz Marina"
        ],
        "start_time": "17:00",
        "end_time": "17:50"
      }
    }
  },
  "sections": [
    "A"
  ]
}
