{
  "code": "GPPS 476",
  "name": "Chinese Sources and Methods",
  "department": "GPPS",
  "id": "476",
  "notes": [],
  "events_single": {},
  "events_unknown": [],
  "events_repeating": {
    "M": {
      "7cf5cca73112253f00cf56fe7f1ad552addcfc24b63ec400993b6cd5caf77416": {
        "sectxt": true,
        "sectionID": "921739",
        "type": "SE",
        "section": "A00",
        "days": "MW",
        "time": "2:00p-3:20p",
        "building": "RBC",
        "room": "1401",
        "instructors": [
          "Shih, Victor Chung"
        ],
        "start_time": "14:00",
        "end_time": "15:20"
      }
    },
    "W": {
      "ca9bd30bf42e370872fc2fb493760a01afec55bf2085cadbc7f27843c2abb8ea": {
        "sectxt": true,
        "sectionID": "921739",
        "type": "SE",
        "section": "A00",
        "days": "MW",
        "time": "2:00p-3:20p",
        "building": "RBC",
        "room": "1401",
        "instructors": [
          "Shih, Victor Chung"
        ],
        "start_time": "14:00",
        "end_time": "15:20"
      }
    }
  },
  "sections": [
    "A"
  ]
}
