{
  "code": "LIGM 1B",
  "name": "German Conversation",
  "department": "LIGM",
  "id": "1B",
  "notes": [],
  "events_single": {},
  "events_unknown": [],
  "events_repeating": {
    "M": {
      "91cdd5bfbe58132c7696c89e3f1185a89d21f3b426e2972524e103f2e4b55e63": {
        "sectxt": true,
        "sectionID": "921323",
        "type": "TU",
        "section": "F00",
        "days": "MWF",
        "time": "2:00p-2:50p",
        "building": "HSS",
        "room": "1106A",
        "instructors": [
          "Riebeling, Elke"
        ],
        "start_time": "14:00",
        "end_time": "14:50"
      },
      "47ad2d8f93ef788a976019581bbef35a64ba090c5e8190c0946ef56ad705a7e3": {
        "sectxt": true,
        "sectionID": "921318",
        "type": "TU",
        "section": "A00",
        "days": "MWF",
        "time": "9:00a-9:50a",
        "building": "HSS",
        "room": "1106A",
        "instructors": [
          "Riebeling, Elke"
        ],
        "start_time": "09:00",
        "end_time": "09:50"
      },
      "02afafb665098aeb563139063c2ee51983af334d11144eafe9f031d13a03681c": {
        "sectxt": true,
        "sectionID": "921319",
        "type": "TU",
        "section": "B00",
        "days": "MWF",
        "time": "10:00a-10:50a",
        "building": "HSS",
        "room": "1106A",
        "instructors": [
          "Riebeling, Elke"
        ],
        "start_time": "10:00",
        "end_time": "10:50"
      },
      "d598f368423ca9519e3353580942bf15a7ecf0b60e522a48edd44bad9227743b": {
        "sectxt": true,
        "sectionID": "921320",
        "type": "TU",
        "section": "C00",
        "days": "MWF",
        "time": "11:00a-11:50a",
        "building": "HSS",
        "room": "1106A",
        "instructors": [
          "Riebeling, Elke"
        ],
        "start_time": "11:00",
        "end_time": "11:50"
      },
      "add86cb4bc36a64c5bddb36fc364f54b23833a5e0df5be3edb60ef9b011976ea": {
        "sectxt": true,
        "sectionID": "921321",
        "type": "TU",
        "section": "D00",
        "days": "MWF",
        "time": "12:00p-12:50p",
        "building": "HSS",
        "room": "1106A",
        "instructors": [
          "Riebeling, Elke"
        ],
        "start_time": "12:00",
        "end_time": "12:50"
      },
      "574f56bf481a7d6e5d938a2c725dcd595c0c7e5cac62af114d67d2463223099f": {
        "sectxt": true,
        "sectionID": "921322",
        "type": "TU",
        "section": "E00",
        "days": "MWF",
        "time": "1:00p-1:50p",
        "building": "HSS",
        "room": "1106A",
        "instructors": [
          "Riebeling, Elke"
        ],
        "start_time": "13:00",
        "end_time": "13:50"
      }
    },
    "W": {
      "7054e8d2f3e5360dbd873fb8f9ff61f6c08f392d9f86d58756205f0f06e8d21d": {
        "sectxt": true,
        "sectionID": "921323",
        "type": "TU",
        "section": "F00",
        "days": "MWF",
        "time": "2:00p-2:50p",
        "building": "HSS",
        "room": "1106A",
        "instructors": [
          "Riebeling, Elke"
        ],
        "start_time": "14:00",
        "end_time": "14:50"
      },
      "3eb179c9f1877b143d95b0e3207aa88a4b04aa93296de8e1c606543a0cc5e21d": {
        "sectxt": true,
        "sectionID": "921318",
        "type": "TU",
        "section": "A00",
        "days": "MWF",
        "time": "9:00a-9:50a",
        "building": "HSS",
        "room": "1106A",
        "instructors": [
          "Riebeling, Elke"
        ],
        "start_time": "09:00",
        "end_time": "09:50"
      },
      "884079ef24644bf946e7cd5145e14b2706aeae41d3d4f5e991031e190cb21874": {
        "sectxt": true,
        "sectionID": "921319",
        "type": "TU",
        "section": "B00",
        "days": "MWF",
        "time": "10:00a-10:50a",
        "building": "HSS",
        "room": "1106A",
        "instructors": [
          "Riebeling, Elke"
        ],
        "start_time": "10:00",
        "end_time": "10:50"
      },
      "1aa5a272ef51c859e44d5cdac659d0a957d708008bc160486622645cc9c10408": {
        "sectxt": true,
        "sectionID": "921320",
        "type": "TU",
        "section": "C00",
        "days": "MWF",
        "time": "11:00a-11:50a",
        "building": "HSS",
        "room": "1106A",
        "instructors": [
          "Riebeling, Elke"
        ],
        "start_time": "11:00",
        "end_time": "11:50"
      },
      "b240d01672710facacf4c78e33bd88fcf8338faf4ce3f9c4de94a1f2a0e7515d": {
        "sectxt": true,
        "sectionID": "921321",
        "type": "TU",
        "section": "D00",
        "days": "MWF",
        "time": "12:00p-12:50p",
        "building": "HSS",
        "room": "1106A",
        "instructors": [
          "Riebeling, Elke"
        ],
        "start_time": "12:00",
        "end_time": "12:50"
      },
      "0c740fa30fa1b124833f584bd2751e5c9f772bb2de20b81034f272dbf0c864f9": {
        "sectxt": true,
        "sectionID": "921322",
        "type": "TU",
        "section": "E00",
        "days": "MWF",
        "time": "1:00p-1:50p",
        "building": "HSS",
        "room": "1106A",
        "instructors": [
          "Riebeling, Elke"
        ],
        "start_time": "13:00",
        "end_time": "13:50"
      }
    },
    "F": {
      "c161495b00f1ebac2f5431d0c3ca72836f6c62c6c7d42362207dd15afc3a5644": {
        "sectxt": true,
        "sectionID": "921323",
        "type": "TU",
        "section": "F00",
        "days": "MWF",
        "time": "2:00p-2:50p",
        "building": "HSS",
        "room": "1106A",
        "instructors": [
          "Riebeling, Elke"
        ],
        "start_time": "14:00",
        "end_time": "14:50"
      },
      "dafdabcae21d3367f807626e634e9a6743cf440cb30134438ac64fe950d485fe": {
        "sectxt": true,
        "sectionID": "921318",
        "type": "TU",
        "section": "A00",
        "days": "MWF",
        "time": "9:00a-9:50a",
        "building": "HSS",
        "room": "1106A",
        "instructors": [
          "Riebeling, Elke"
        ],
        "start_time": "09:00",
        "end_time": "09:50"
      },
      "279deb5c83eeea38278bf8605ad94cace495621586d26eb03fc3fb72c200a2ee": {
        "sectxt": true,
        "sectionID": "921319",
        "type": "TU",
        "section": "B00",
        "days": "MWF",
        "time": "10:00a-10:50a",
        "building": "HSS",
        "room": "1106A",
        "instructors": [
          "Riebeling, Elke"
        ],
        "start_time": "10:00",
        "end_time": "10:50"
      },
      "ccda22a392509642ce5f69ce8567d771b23871598091b90a476243ed8a3d129c": {
        "sectxt": true,
        "sectionID": "921320",
        "type": "TU",
        "section": "C00",
        "days": "MWF",
        "time": "11:00a-11:50a",
        "building": "HSS",
        "room": "1106A",
        "instructors": [
          "Riebeling, Elke"
        ],
        "start_time": "11:00",
        "end_time": "11:50"
      },
      "ddb3a49aa9119ec51062d292244a061252deb43b38afdfa24c87561af3569c4a": {
        "sectxt": true,
        "sectionID": "921321",
        "type": "TU",
        "section": "D00",
        "days": "MWF",
        "time": "12:00p-12:50p",
        "building": "HSS",
        "room": "1106A",
        "instructors": [
          "Riebeling, Elke"
        ],
        "start_time": "12:00",
        "end_time": "12:50"
      },
      "7582b18af329fb7ec114ceab0ced93cbeb7e96f24e07e1c545822f4032e775f0": {
        "sectxt": true,
        "sectionID": "921322",
        "type": "TU",
        "section": "E00",
        "days": "MWF",
        "time": "1:00p-1:50p",
        "building": "HSS",
        "room": "1106A",
        "instructors": [
          "Riebeling, Elke"
        ],
        "start_time": "13:00",
        "end_time": "13:50"
      }
    }
  },
  "sections": [
    "A",
    "B",
    "C",
    "D",
    "E",
    "F"
  ]
}
