{
  "code": "LTKO 1B",
  "name": "Beginning Korean:First Yr. II",
  "department": "LTKO",
  "id": "1B",
  "notes": [],
  "events_single": {
    "4fbe707a38ddc20578e570192f103e51846d1628ae7ba4746a2d53526ba0b2bc": {
      "sectxt": false,
      "sectionID": "",
      "type": "FI",
      "section": "03/19/2018",
      "days": "M",
      "time": "3:00p-5:59p",
      "building": "TBA",
      "room": "TBA",
      "instructors": [],
      "date": "2018-03-19T07:00:00.000Z",
      "start_time": "15:00",
      "end_time": "17:59"
    },
    "e2c5234a701d27574e15aa0904159f53979408c2b1ae53d9c26e357d7d24786c": {
      "sectxt": false,
      "sectionID": "",
      "type": "FI",
      "section": "03/21/2018",
      "days": "W",
      "time": "8:00a-10:59a",
      "building": "TBA",
      "room": "TBA",
      "instructors": [],
      "date": "2018-03-21T07:00:00.000Z",
      "start_time": "08:00",
      "end_time": "10:59"
    },
    "d28840bdf73115119139b7b7848608232d0324e6ce8e0183d1201a3dbf9b5121": {
      "sectxt": false,
      "sectionID": "",
      "type": "FI",
      "section": "03/23/2018",
      "days": "F",
      "time": "8:00a-10:59a",
      "building": "TBA",
      "room": "TBA",
      "instructors": [],
      "date": "2018-03-23T07:00:00.000Z",
      "start_time": "08:00",
      "end_time": "10:59"
    },
    "314651a9d552154e29cad7ff987d1489707c596a65381c644affb7524a5a2410": {
      "sectxt": false,
      "sectionID": "",
      "type": "FI",
      "section": "03/19/2018",
      "days": "M",
      "time": "11:30a-2:29p",
      "building": "TBA",
      "room": "TBA",
      "instructors": [],
      "date": "2018-03-19T07:00:00.000Z",
      "start_time": "11:30",
      "end_time": "14:29"
    },
    "b77cfdf2b687e33c7cc177500c81fd38191db9611a36a223e3e2850d43cd535b": {
      "sectxt": false,
      "sectionID": "",
      "type": "FI",
      "section": "03/21/2018",
      "days": "W",
      "time": "11:30a-2:29p",
      "building": "TBA",
      "room": "TBA",
      "instructors": [],
      "date": "2018-03-21T07:00:00.000Z",
      "start_time": "11:30",
      "end_time": "14:29"
    },
    "c4c6f714d90adf7eacccfcc7efbb870149ec8d367e016a27af6ed2d4b5d2095c": {
      "sectxt": false,
      "sectionID": "",
      "type": "FI",
      "section": "03/23/2018",
      "days": "F",
      "time": "11:30a-2:29p",
      "building": "TBA",
      "room": "TBA",
      "instructors": [],
      "date": "2018-03-23T07:00:00.000Z",
      "start_time": "11:30",
      "end_time": "14:29"
    }
  },
  "events_unknown": [],
  "events_repeating": {
    "M": {
      "9cffd06e620c62969429788c49c7e2a66a451bd13a9edc346e1926be82b8c736": {
        "sectxt": true,
        "sectionID": "",
        "type": "LE",
        "section": "Q00",
        "days": "MWF",
        "time": "2:00p-2:50p",
        "building": "CENTR",
        "room": "203",
        "instructors": [
          "Lee, Jeyseon"
        ],
        "start_time": "14:00",
        "end_time": "14:50"
      },
      "c523561511bba2b050b1083c655ac2decedabe9ec55178d25a58ccfb8310f4f4": {
        "sectxt": true,
        "sectionID": "",
        "type": "LE",
        "section": "A00",
        "days": "MWF",
        "time": "9:00a-9:50a",
        "building": "CENTR",
        "room": "203",
        "instructors": [
          "Lee, Jeyseon"
        ],
        "start_time": "09:00",
        "end_time": "09:50"
      },
      "d0b2fffe246dca3025dae4dede067c9e29ea987a4c14f50d1521b640d91f1845": {
        "sectxt": true,
        "sectionID": "",
        "type": "LE",
        "section": "M00",
        "days": "MWF",
        "time": "10:00a-10:50a",
        "building": "CENTR",
        "room": "203",
        "instructors": [
          "Lee, Jeyseon"
        ],
        "start_time": "10:00",
        "end_time": "10:50"
      },
      "decd3bf8a5cd907b3c7caf084151af3875052b63c46f7c4bb593fae9c4f9d903": {
        "sectxt": true,
        "sectionID": "",
        "type": "LE",
        "section": "N00",
        "days": "MWF",
        "time": "11:00a-11:50a",
        "building": "CENTR",
        "room": "203",
        "instructors": [
          "Lee, Jeyseon"
        ],
        "start_time": "11:00",
        "end_time": "11:50"
      },
      "960d5b458714f9836de687936dfaa893337abd6dde31c1d0bc9ef54abcf75283": {
        "sectxt": true,
        "sectionID": "",
        "type": "LE",
        "section": "O00",
        "days": "MWF",
        "time": "12:00p-12:50p",
        "building": "CENTR",
        "room": "203",
        "instructors": [
          "Lee, Jeyseon"
        ],
        "start_time": "12:00",
        "end_time": "12:50"
      },
      "67cb7d6b85f2a56d5ac32e99fa6018c0727a47494d24c372ac938954c5fe5b4f": {
        "sectxt": true,
        "sectionID": "",
        "type": "LE",
        "section": "P00",
        "days": "MWF",
        "time": "1:00p-1:50p",
        "building": "CENTR",
        "room": "203",
        "instructors": [
          "Lee, Jeyseon"
        ],
        "start_time": "13:00",
        "end_time": "13:50"
      }
    },
    "Tu": {
      "e459a58cb5e048515cffbb3312fe8c5fe9609d30f87cf199a4a9ff249e07899d": {
        "sectxt": true,
        "sectionID": "920115",
        "type": "DI",
        "section": "Q01",
        "days": "TuTh",
        "time": "2:00p-2:50p",
        "building": "CENTR",
        "room": "203",
        "instructors": [
          "Lee, Jeyseon"
        ],
        "start_time": "14:00",
        "end_time": "14:50"
      },
      "e6889bb4a5a21d0f117822291505337fddf821d936813a467ab0ef3b6e3782ae": {
        "sectxt": true,
        "sectionID": "920105",
        "type": "DI",
        "section": "A01",
        "days": "TuTh",
        "time": "9:00a-9:50a",
        "building": "CENTR",
        "room": "203",
        "instructors": [
          "Lee, Jeyseon"
        ],
        "start_time": "09:00",
        "end_time": "09:50"
      },
      "7d93bffcba87b61208a5c5cd0f69e3618483443d66e5f2fdba34219b9fc6eb5a": {
        "sectxt": true,
        "sectionID": "920107",
        "type": "DI",
        "section": "M01",
        "days": "TuTh",
        "time": "10:00a-10:50a",
        "building": "CENTR",
        "room": "203",
        "instructors": [
          "Lee, Jeyseon"
        ],
        "start_time": "10:00",
        "end_time": "10:50"
      },
      "a82ba473be24e4a9e0e8088e1b1367083d5211ade5d417caf8424437f8a76986": {
        "sectxt": true,
        "sectionID": "920109",
        "type": "DI",
        "section": "N01",
        "days": "TuTh",
        "time": "11:00a-11:50a",
        "building": "CENTR",
        "room": "203",
        "instructors": [
          "Lee, Jeyseon"
        ],
        "start_time": "11:00",
        "end_time": "11:50"
      },
      "da36dd931ba836796acc2f63d72dd018e9b26fbe0019379217613685f9a74e68": {
        "sectxt": true,
        "sectionID": "920111",
        "type": "DI",
        "section": "O01",
        "days": "TuTh",
        "time": "12:00p-12:50p",
        "building": "CENTR",
        "room": "203",
        "instructors": [
          "Lee, Jeyseon"
        ],
        "start_time": "12:00",
        "end_time": "12:50"
      },
      "bb4e35390172f67e0d6d8d66991da590d8b1f6658750b533484ced763361ab2a": {
        "sectxt": true,
        "sectionID": "920113",
        "type": "DI",
        "section": "P01",
        "days": "TuTh",
        "time": "1:00p-1:50p",
        "building": "CENTR",
        "room": "203",
        "instructors": [
          "Lee, Jeyseon"
        ],
        "start_time": "13:00",
        "end_time": "13:50"
      }
    },
    "W": {
      "3614352d3679983cbaf10478b84e337bd8c6ac384016c159cb93c1daed435b2c": {
        "sectxt": true,
        "sectionID": "",
        "type": "LE",
        "section": "Q00",
        "days": "MWF",
        "time": "2:00p-2:50p",
        "building": "CENTR",
        "room": "203",
        "instructors": [
          "Lee, Jeyseon"
        ],
        "start_time": "14:00",
        "end_time": "14:50"
      },
      "7eed7cb66e17d287be5988a2241d6bb3c9022ed1a35b7d3a11b9287ac809c3bb": {
        "sectxt": true,
        "sectionID": "",
        "type": "LE",
        "section": "A00",
        "days": "MWF",
        "time": "9:00a-9:50a",
        "building": "CENTR",
        "room": "203",
        "instructors": [
          "Lee, Jeyseon"
        ],
        "start_time": "09:00",
        "end_time": "09:50"
      },
      "35b20b232cfe844db45aede9ce425377107ab85d16ed25f418d3bb7c1a07b09d": {
        "sectxt": true,
        "sectionID": "",
        "type": "LE",
        "section": "M00",
        "days": "MWF",
        "time": "10:00a-10:50a",
        "building": "CENTR",
        "room": "203",
        "instructors": [
          "Lee, Jeyseon"
        ],
        "start_time": "10:00",
        "end_time": "10:50"
      },
      "d6d8cde2ea6a1cafe3fb857df12f21fd2fa37c98addde1ccdba7e1b051bdc609": {
        "sectxt": true,
        "sectionID": "",
        "type": "LE",
        "section": "N00",
        "days": "MWF",
        "time": "11:00a-11:50a",
        "building": "CENTR",
        "room": "203",
        "instructors": [
          "Lee, Jeyseon"
        ],
        "start_time": "11:00",
        "end_time": "11:50"
      },
      "95d3ddfb922c2c730e46b4ff4dfb8034f9c20b827c1ee898039e01c2388852a5": {
        "sectxt": true,
        "sectionID": "",
        "type": "LE",
        "section": "O00",
        "days": "MWF",
        "time": "12:00p-12:50p",
        "building": "CENTR",
        "room": "203",
        "instructors": [
          "Lee, Jeyseon"
        ],
        "start_time": "12:00",
        "end_time": "12:50"
      },
      "27d67cb43f49892106e4834e14f3bdc05e7e2c80e94bfe5519508dbc752de558": {
        "sectxt": true,
        "sectionID": "",
        "type": "LE",
        "section": "P00",
        "days": "MWF",
        "time": "1:00p-1:50p",
        "building": "CENTR",
        "room": "203",
        "instructors": [
          "Lee, Jeyseon"
        ],
        "start_time": "13:00",
        "end_time": "13:50"
      }
    },
    "Th": {
      "1ab511af2d7494be560e3f5dcda6e0b0cbf006555d2f6bfd7c0be930255a764c": {
        "sectxt": true,
        "sectionID": "920115",
        "type": "DI",
        "section": "Q01",
        "days": "TuTh",
        "time": "2:00p-2:50p",
        "building": "CENTR",
        "room": "203",
        "instructors": [
          "Lee, Jeyseon"
        ],
        "start_time": "14:00",
        "end_time": "14:50"
      },
      "b0d4cc7f83f3088a155898ea7b40b7baaa797b149b69051b58b9f01673a6d4b8": {
        "sectxt": true,
        "sectionID": "920105",
        "type": "DI",
        "section": "A01",
        "days": "TuTh",
        "time": "9:00a-9:50a",
        "building": "CENTR",
        "room": "203",
        "instructors": [
          "Lee, Jeyseon"
        ],
        "start_time": "09:00",
        "end_time": "09:50"
      },
      "62c926f868fa62dfbbfa640549bb72a21e1f81d604c30653a6be706c9ccf36e0": {
        "sectxt": true,
        "sectionID": "920107",
        "type": "DI",
        "section": "M01",
        "days": "TuTh",
        "time": "10:00a-10:50a",
        "building": "CENTR",
        "room": "203",
        "instructors": [
          "Lee, Jeyseon"
        ],
        "start_time": "10:00",
        "end_time": "10:50"
      },
      "426fefe24fc1ec8ef210a280bdd55fd7044bbb822779c0fee8857ea7ca801d36": {
        "sectxt": true,
        "sectionID": "920109",
        "type": "DI",
        "section": "N01",
        "days": "TuTh",
        "time": "11:00a-11:50a",
        "building": "CENTR",
        "room": "203",
        "instructors": [
          "Lee, Jeyseon"
        ],
        "start_time": "11:00",
        "end_time": "11:50"
      },
      "5beb45a907dee58407706440a5a8f4c29db071e4b0b6f1492617ab999ac479b3": {
        "sectxt": true,
        "sectionID": "920111",
        "type": "DI",
        "section": "O01",
        "days": "TuTh",
        "time": "12:00p-12:50p",
        "building": "CENTR",
        "room": "203",
        "instructors": [
          "Lee, Jeyseon"
        ],
        "start_time": "12:00",
        "end_time": "12:50"
      },
      "10c2a8f43b6c6cb9d4b4d882bd27ae7efcd929fd9171538cc3a04638eb843e64": {
        "sectxt": true,
        "sectionID": "920113",
        "type": "DI",
        "section": "P01",
        "days": "TuTh",
        "time": "1:00p-1:50p",
        "building": "CENTR",
        "room": "203",
        "instructors": [
          "Lee, Jeyseon"
        ],
        "start_time": "13:00",
        "end_time": "13:50"
      }
    },
    "F": {
      "0f0bff528cc3033061f5609a3c5df161decf54f1c9169a525f4daf4baef73b6c": {
        "sectxt": true,
        "sectionID": "",
        "type": "LE",
        "section": "Q00",
        "days": "MWF",
        "time": "2:00p-2:50p",
        "building": "CENTR",
        "room": "203",
        "instructors": [
          "Lee, Jeyseon"
        ],
        "start_time": "14:00",
        "end_time": "14:50"
      },
      "b7f3399de03e3590eaec1dea9fb9eee1729ccb543e3d159d38a0cedf1b331f51": {
        "sectxt": true,
        "sectionID": "",
        "type": "LE",
        "section": "A00",
        "days": "MWF",
        "time": "9:00a-9:50a",
        "building": "CENTR",
        "room": "203",
        "instructors": [
          "Lee, Jeyseon"
        ],
        "start_time": "09:00",
        "end_time": "09:50"
      },
      "1f18fa39a1392e8cd61f17e062861564e21a24395a695d4b0e22be57b266949d": {
        "sectxt": true,
        "sectionID": "",
        "type": "LE",
        "section": "M00",
        "days": "MWF",
        "time": "10:00a-10:50a",
        "building": "CENTR",
        "room": "203",
        "instructors": [
          "Lee, Jeyseon"
        ],
        "start_time": "10:00",
        "end_time": "10:50"
      },
      "13fb44da6b88b5998b447164130998060ec2f1658b42bed582567f367c98c09b": {
        "sectxt": true,
        "sectionID": "",
        "type": "LE",
        "section": "N00",
        "days": "MWF",
        "time": "11:00a-11:50a",
        "building": "CENTR",
        "room": "203",
        "instructors": [
          "Lee, Jeyseon"
        ],
        "start_time": "11:00",
        "end_time": "11:50"
      },
      "531461453ffa43c6232a50c2349d7025c2bc27139d9b7cbe58787b88d64636ec": {
        "sectxt": true,
        "sectionID": "",
        "type": "LE",
        "section": "O00",
        "days": "MWF",
        "time": "12:00p-12:50p",
        "building": "CENTR",
        "room": "203",
        "instructors": [
          "Lee, Jeyseon"
        ],
        "start_time": "12:00",
        "end_time": "12:50"
      },
      "a07a87a56dd3bcb98c437898d9b956264328d328c61122fbfecd9ea42d35965f": {
        "sectxt": true,
        "sectionID": "",
        "type": "LE",
        "section": "P00",
        "days": "MWF",
        "time": "1:00p-1:50p",
        "building": "CENTR",
        "room": "203",
        "instructors": [
          "Lee, Jeyseon"
        ],
        "start_time": "13:00",
        "end_time": "13:50"
      }
    }
  },
  "sections": [
    "Q",
    "R",
    "A",
    "M",
    "N",
    "O",
    "P"
  ]
}
