{
  "code": "MAE 285",
  "name": "Micro/Nanoacoustofluidic Dvcs",
  "department": "MAE",
  "id": "285",
  "notes": [],
  "events_single": {
    "6667c9d80c15defdb42d852140b9c713b56b6df53bdf3eafefaea44b723c8ac9": {
      "sectxt": false,
      "sectionID": "",
      "type": "FI",
      "section": "03/21/2018",
      "days": "W",
      "time": "8:00a-10:59a",
      "building": "TBA",
      "room": "TBA",
      "instructors": [],
      "date": "2018-03-21T07:00:00.000Z",
      "start_time": "08:00",
      "end_time": "10:59"
    }
  },
  "events_unknown": [],
  "events_repeating": {
    "M": {
      "36c92b79bb18c40f9c7a0106f09fd7cea2b06410a74ae6658c7e02e62a8ac46f": {
        "sectxt": true,
        "sectionID": "930087",
        "type": "LE",
        "section": "A00",
        "days": "M",
        "time": "9:00a-11:50a",
        "building": "EBU2",
        "room": "105",
        "instructors": [
          "Friend, James Robert"
        ],
        "start_time": "09:00",
        "end_time": "11:50"
      }
    }
  },
  "sections": [
    "A"
  ]
}
