{
  "code": "MATS 201B",
  "name": "Solid State Diff&Reac Kinetics",
  "department": "MATS",
  "id": "201B",
  "notes": [],
  "events_single": {
    "95d1ec72a1d19dcd18f35456264e151708a4c53139264908dc5d4d46ab035a80": {
      "sectxt": false,
      "sectionID": "",
      "type": "FI",
      "section": "03/20/2018",
      "days": "Tu",
      "time": "3:00p-5:59p",
      "building": "TBA",
      "room": "TBA",
      "instructors": [],
      "date": "2018-03-20T07:00:00.000Z",
      "start_time": "15:00",
      "end_time": "17:59"
    }
  },
  "events_unknown": [],
  "events_repeating": {
    "Tu": {
      "aae6afee574bb9571004d959a4bd8e14669c0f15c2a5ef2362460aa52d0809f4": {
        "sectxt": true,
        "sectionID": "920838",
        "type": "LE",
        "section": "A00",
        "days": "TuTh",
        "time": "3:30p-4:50p",
        "building": "CSB",
        "room": "002",
        "instructors": [
          "McKittrick, Joanna M"
        ],
        "start_time": "15:30",
        "end_time": "16:50"
      }
    },
    "Th": {
      "45a60f70a6203d439d2c045643588de3af70d095159a6a81fd8b8f3e081e38c3": {
        "sectxt": true,
        "sectionID": "920838",
        "type": "LE",
        "section": "A00",
        "days": "TuTh",
        "time": "3:30p-4:50p",
        "building": "CSB",
        "room": "002",
        "instructors": [
          "McKittrick, Joanna M"
        ],
        "start_time": "15:30",
        "end_time": "16:50"
      }
    }
  },
  "sections": [
    "A"
  ]
}
