{
  "code": "MUS 130",
  "name": "Chamber Music Performance",
  "department": "MUS",
  "id": "130",
  "notes": [],
  "events_single": {
    "b58675fb24fe9227cdf82d5642bfd9551cacca01c3bb7011ea1e411f0e6c9efe": {
      "sectxt": false,
      "sectionID": "",
      "type": "FI",
      "section": "03/22/2018",
      "days": "Th",
      "time": "3:00p-5:59p",
      "building": "TBA",
      "room": "TBA",
      "instructors": [],
      "date": "2018-03-22T07:00:00.000Z",
      "start_time": "15:00",
      "end_time": "17:59"
    }
  },
  "events_unknown": [],
  "events_repeating": {
    "Th": {
      "0db3a78e8d543ebfb68f32e80fc266d477dc9fd574c8eb19ed9072c299fc69d5": {
        "sectxt": true,
        "sectionID": "921809",
        "type": "ST",
        "section": "A00",
        "days": "Th",
        "time": "2:00p-4:50p",
        "building": "CPMC",
        "room": "368",
        "instructors": [
          "Ohnishi, Takae"
        ],
        "start_time": "14:00",
        "end_time": "16:50"
      }
    }
  },
  "sections": [
    "A"
  ]
}
