{
  "code": "MUS 95E",
  "name": "Chamber Orchestra",
  "department": "MUS",
  "id": "95E",
  "notes": [],
  "events_single": {},
  "events_unknown": [],
  "events_repeating": {
    "Tu": {
      "a78e626b559a5fc40a1698afbac48f1905228d39db7b04a66f0d191ecd34f920": {
        "sectxt": true,
        "sectionID": "921924",
        "type": "ST",
        "section": "A00",
        "days": "Tu",
        "time": "6:30p-9:20p",
        "building": "CPMC",
        "room": "136",
        "instructors": [
          "Kline, Matthew John"
        ],
        "start_time": "18:30",
        "end_time": "21:20"
      }
    }
  },
  "sections": [
    "A"
  ]
}
