{
  "code": "PHAR 255",
  "name": "Moleculr/Drug &Disease Therapy",
  "department": "PHAR",
  "id": "255",
  "notes": [],
  "events_single": {
    "d40ba12c206fa102b440da849e3034c732e524b840d311d80922c015692981c1": {
      "sectxt": false,
      "sectionID": "",
      "type": "FI",
      "section": "03/24/2018",
      "days": "S",
      "time": "8:00a-10:59a",
      "building": "TBA",
      "room": "TBA",
      "instructors": [],
      "date": "2018-03-24T07:00:00.000Z",
      "start_time": "08:00",
      "end_time": "10:59"
    }
  },
  "events_unknown": [],
  "events_repeating": {
    "Tu": {
      "0ab55aa8d4c68c4b610adb6c040193e7317e2cc10fbdfb88b76be08cd26ef77a": {
        "sectxt": true,
        "sectionID": "930036",
        "type": "LE",
        "section": "A00",
        "days": "TuTh",
        "time": "10:00a-11:50a",
        "building": "CMME",
        "room": "2047",
        "instructors": [
          "Handel, Tracy                      \n\t\t\t\t\t\t\t\t\t\t\t\t\t\t\t\t\t\t\t\t\t\t\t\t\n\t\t\t\t\t\t\t\t\t\t\t\t\t\t\t\t\t\t\t\t\t\t\t\t\n\t\t\t\t\t\t\t\t\t\t\t\t\t\t\t\t\t\t\t\t\t\t\t\n\t\t\t\t\t\t\t\t\t\t\t\t\t\t\t\t\t\t\t\t\t\t\t\n\t\t\t\t\t\t\t\t\t\t\t\t\t\t\t\t\t\t\t\t\t\t\n\t\t\t\t\t\t\t\t\t\t\t\t\t\t\t\t\t\t\t\t\t\t\t\n\t\t\t\t\t\t\t\t\t\t\t\t\t\t\t\t\t\t\t\t\t\t\t\t\n\t\t\t\t\t\t\t\t\t\t\t\t\t\t\t\t\t\t\t\t\t\t\t\t\tGutkind, Jorge Silvio              \n\t\t\t\t\t\t\t\t\t\t\t\t\t\t\t\t\t\t\t\t\t\t\t\t\n\t\t\t\t\t\t\t\t\t\t\t\t\t\t\t\t\t\t\t\t\t\t\t\t\n\t\t\t\t\t\t\t\t\t\t\t\t\t\t\t\t\t\t\t\t\t\t\t\n\t\t\t\t\t\t\t\t\t\t\t\t\t\t\t\t\t\t\t\t\t\t\t\n\t\t\t\t\t\t\t\t\t\t\t\t\t\t\t\t\t\t\t\t\t\t\n\t\t\t\t\t\t\t\t\t\t\t\t\t\t\t\t\t\t\t\t\t\t\t\n\t\t\t\t\t\t\t\t\t\t\t\t\t\t\t\t\t\t\t\t\t\t\t\t\n\t\t\t\t\t\t\t\t\t\t\t\t\t\t\t\t\t\t\t\t\t\t\t\t\tVallon, Volker"
        ],
        "start_time": "10:00",
        "end_time": "11:50"
      }
    },
    "Th": {
      "ddb7d18e2d76f661e3d1746d14a8dded5d85630415a380a45790bc4bc2018c1b": {
        "sectxt": true,
        "sectionID": "930036",
        "type": "LE",
        "section": "A00",
        "days": "TuTh",
        "time": "10:00a-11:50a",
        "building": "CMME",
        "room": "2047",
        "instructors": [
          "Handel, Tracy                      \n\t\t\t\t\t\t\t\t\t\t\t\t\t\t\t\t\t\t\t\t\t\t\t\t\n\t\t\t\t\t\t\t\t\t\t\t\t\t\t\t\t\t\t\t\t\t\t\t\t\n\t\t\t\t\t\t\t\t\t\t\t\t\t\t\t\t\t\t\t\t\t\t\t\n\t\t\t\t\t\t\t\t\t\t\t\t\t\t\t\t\t\t\t\t\t\t\t\n\t\t\t\t\t\t\t\t\t\t\t\t\t\t\t\t\t\t\t\t\t\t\n\t\t\t\t\t\t\t\t\t\t\t\t\t\t\t\t\t\t\t\t\t\t\t\n\t\t\t\t\t\t\t\t\t\t\t\t\t\t\t\t\t\t\t\t\t\t\t\t\n\t\t\t\t\t\t\t\t\t\t\t\t\t\t\t\t\t\t\t\t\t\t\t\t\tGutkind, Jorge Silvio              \n\t\t\t\t\t\t\t\t\t\t\t\t\t\t\t\t\t\t\t\t\t\t\t\t\n\t\t\t\t\t\t\t\t\t\t\t\t\t\t\t\t\t\t\t\t\t\t\t\t\n\t\t\t\t\t\t\t\t\t\t\t\t\t\t\t\t\t\t\t\t\t\t\t\n\t\t\t\t\t\t\t\t\t\t\t\t\t\t\t\t\t\t\t\t\t\t\t\n\t\t\t\t\t\t\t\t\t\t\t\t\t\t\t\t\t\t\t\t\t\t\n\t\t\t\t\t\t\t\t\t\t\t\t\t\t\t\t\t\t\t\t\t\t\t\n\t\t\t\t\t\t\t\t\t\t\t\t\t\t\t\t\t\t\t\t\t\t\t\t\n\t\t\t\t\t\t\t\t\t\t\t\t\t\t\t\t\t\t\t\t\t\t\t\t\tVallon, Volker"
        ],
        "start_time": "10:00",
        "end_time": "11:50"
      }
    }
  },
  "sections": [
    "A"
  ]
}
