{
  "code": "PHYS 130C",
  "name": "Quantum Physics III",
  "department": "PHYS",
  "id": "130C",
  "notes": [],
  "events_single": {
    "030a218f4d4e48e01627fc0c500d5de9e83bf58c306370911e0d98744bcc7f69": {
      "sectxt": false,
      "sectionID": "",
      "type": "FI",
      "section": "03/23/2018",
      "days": "F",
      "time": "8:00a-10:59a",
      "building": "TBA",
      "room": "TBA",
      "instructors": [],
      "date": "2018-03-23T07:00:00.000Z",
      "start_time": "8:00",
      "end_time": "10:59"
    }
  },
  "events_unknown": [],
  "events_repeating": {
    "M": {
      "af295f2974e1fc813c8c3c89f9557ca6d3bebef0efbf5f2c104d8a24f24daf57": {
        "sectxt": true,
        "sectionID": "",
        "type": "LE",
        "section": "A00",
        "days": "MWF",
        "time": "10:00a-10:50a",
        "building": "MYR-A",
        "room": "2623",
        "instructors": [
          "Branson, James G"
        ],
        "start_time": "10:00",
        "end_time": "10:50"
      }
    },
    "W": {
      "b19f6a35e9d4b5884b1fbbcadb0f64def417f94f4a1279e960ebba1828651078": {
        "sectxt": true,
        "sectionID": "",
        "type": "LE",
        "section": "A00",
        "days": "MWF",
        "time": "10:00a-10:50a",
        "building": "MYR-A",
        "room": "2623",
        "instructors": [
          "Branson, James G"
        ],
        "start_time": "10:00",
        "end_time": "10:50"
      }
    },
    "F": {
      "2d0cbc9763c7fbda8b2ce93c6ff55afe3346db8e6b0eab70e43f87ae10a7b063": {
        "sectxt": true,
        "sectionID": "",
        "type": "LE",
        "section": "A00",
        "days": "MWF",
        "time": "10:00a-10:50a",
        "building": "MYR-A",
        "room": "2623",
        "instructors": [
          "Branson, James G"
        ],
        "start_time": "10:00",
        "end_time": "10:50"
      },
      "046e3f01ad56536df132f89efb594cfd0c07d5f633257df346fe20fcaceafafd": {
        "sectxt": true,
        "sectionID": "923767",
        "type": "DI",
        "section": "A01",
        "days": "F",
        "time": "11:00a-11:50a",
        "building": "MYR-A",
        "room": "2623",
        "instructors": [
          "Branson, James G"
        ],
        "start_time": "11:00",
        "end_time": "11:50"
      }
    }
  },
  "sections": [
    "A"
  ]
}
