{
  "code": "SOCI 188D",
  "name": "Latin Amer: Society & Politics",
  "department": "SOCI",
  "id": "188D",
  "notes": [],
  "events_single": {
    "cbf511842211ed783639d70cd4e55f8432fd8379bddca74de0606cd449bea2ef": {
      "sectxt": false,
      "sectionID": "",
      "type": "FI",
      "section": "03/20/2018",
      "days": "Tu",
      "time": "11:30a-2:29p",
      "building": "TBA",
      "room": "TBA",
      "instructors": [],
      "date": "2018-03-20T07:00:00.000Z",
      "start_time": "11:30",
      "end_time": "14:29"
    }
  },
  "events_unknown": [],
  "events_repeating": {
    "Tu": {
      "b42e0f2409e12ef4737a5fd409803bcd0e20654786b946951ee70945d729a465": {
        "sectxt": true,
        "sectionID": "923209",
        "type": "LE",
        "section": "A00",
        "days": "TuTh",
        "time": "12:30p-1:50p",
        "building": "CSB",
        "room": "004",
        "instructors": [
          "Zamosc, Leon"
        ],
        "start_time": "12:30",
        "end_time": "13:50"
      }
    },
    "Th": {
      "ebac05e3a9e74a884f51ffd033c5528f7fca3b6cd4ee9fd7882d0b6519bd3e23": {
        "sectxt": true,
        "sectionID": "923209",
        "type": "LE",
        "section": "A00",
        "days": "TuTh",
        "time": "12:30p-1:50p",
        "building": "CSB",
        "room": "004",
        "instructors": [
          "Zamosc, Leon"
        ],
        "start_time": "12:30",
        "end_time": "13:50"
      }
    }
  },
  "sections": [
    "A"
  ]
}
