{
  "code": "VIS 171",
  "name": "Digital Cinema-Theory/Productn",
  "department": "VIS",
  "id": "171",
  "notes": [],
  "events_single": {
    "6ffdc151e1ff47f90f4b9fc5623bdde41c0fbec145605a26c5b8c3446ba98af8": {
      "sectxt": false,
      "sectionID": "",
      "type": "FI",
      "section": "03/20/2018",
      "days": "Tu",
      "time": "11:30a-2:29p",
      "building": "TBA",
      "room": "TBA",
      "instructors": [],
      "date": "2018-03-20T07:00:00.000Z",
      "start_time": "11:30",
      "end_time": "14:29"
    }
  },
  "events_unknown": [],
  "events_repeating": {
    "Tu": {
      "866b8a5fefd5438c47fd1d1cef1a2d026a1f13b84a0642292d9e0687ebd27a54": {
        "sectxt": true,
        "sectionID": "922806",
        "type": "LE",
        "section": "A00",
        "days": "TuTh",
        "time": "12:30p-3:20p",
        "building": "MANDE",
        "room": "103",
        "instructors": [
          "Tonies, Joshua Vanjaymes"
        ],
        "start_time": "12:30",
        "end_time": "15:20"
      }
    },
    "Th": {
      "6de25d431f97fd10879e3b570da032d0e165978b4655b1aae771654275c477c0": {
        "sectxt": true,
        "sectionID": "922806",
        "type": "LE",
        "section": "A00",
        "days": "TuTh",
        "time": "12:30p-3:20p",
        "building": "MANDE",
        "room": "103",
        "instructors": [
          "Tonies, Joshua Vanjaymes"
        ],
        "start_time": "12:30",
        "end_time": "15:20"
      }
    }
  },
  "sections": [
    "A"
  ]
}
